canonicalwebteam/__init__.py
canonicalwebteam/django_views/__init__.py
tests/__init__.py
tests/test_template_finder.py
tests/fixtures/__init__.py
tests/fixtures/urls.py
canonicalwebteam.django_views-1.4.0.dist-info/LICENSE.txt
canonicalwebteam.django_views-1.4.0.dist-info/METADATA
canonicalwebteam.django_views-1.4.0.dist-info/WHEEL
canonicalwebteam.django_views-1.4.0.dist-info/top_level.txt
canonicalwebteam.django_views-1.4.0.dist-info/RECORD
