Metadata-Version: 2.1
Name: canonicalwebteam.django-views
Version: 1.4.0
Summary: Shared Django views for use in Webteam apps
Home-page: https://github.com/canonicalwebteam/django_views
Author: Canonical webteam
Author-email: webteam@canonical.com
License: UNKNOWN
Platform: UNKNOWN
Requires-Dist: mistune
Requires-Dist: python-frontmatter
Requires-Dist: django
